robotoff/__init__.py
robotoff/__main__.py
robotoff/app/__init__.py
robotoff/app/api.py
robotoff/app/auth.py
robotoff/app/core.py
robotoff/app/events.py
robotoff/app/middleware.py
robotoff/app/schema.py
robotoff/brands.py
robotoff/cli/__init__.py
robotoff/cli/file.py
robotoff/cli/insights.py
robotoff/cli/logos.py
robotoff/cli/main.py
robotoff/elasticsearch/__init__.py
robotoff/elasticsearch/client.py
robotoff/elasticsearch/export.py
robotoff/elasticsearch/product/__init__.py
robotoff/elasticsearch/product/dump.py
robotoff/health.py
robotoff/images.py
robotoff/insights/__init__.py
robotoff/insights/annotate.py
robotoff/insights/extraction.py
robotoff/insights/importer.py
robotoff/insights/normalize.py
robotoff/insights/question.py
robotoff/logos.py
robotoff/metrics.py
robotoff/models.py
robotoff/off.py
robotoff/prediction/__init__.py
robotoff/prediction/category/__init__.py
robotoff/prediction/category/matcher.py
robotoff/prediction/category/neural/__init__.py
robotoff/prediction/category/neural/category_classifier.py
robotoff/prediction/category/neural/keras_category_classifier_3_0/__init__.py
robotoff/prediction/category/neural/keras_category_classifier_3_0/preprocessing.py
robotoff/prediction/category/neural/keras_category_classifier_3_0/text_utils.py
robotoff/prediction/langid.py
robotoff/prediction/object_detection/__init__.py
robotoff/prediction/object_detection/core.py
robotoff/prediction/object_detection/utils/__init__.py
robotoff/prediction/object_detection/utils/visualization_utils.py
robotoff/prediction/ocr/__init__.py
robotoff/prediction/ocr/brand.py
robotoff/prediction/ocr/category.py
robotoff/prediction/ocr/core.py
robotoff/prediction/ocr/dataclass.py
robotoff/prediction/ocr/expiration_date.py
robotoff/prediction/ocr/grammar.py
robotoff/prediction/ocr/image_flag.py
robotoff/prediction/ocr/image_lang.py
robotoff/prediction/ocr/image_orientation.py
robotoff/prediction/ocr/label.py
robotoff/prediction/ocr/location.py
robotoff/prediction/ocr/nutrient.py
robotoff-1.28.0.dist-info/entry_points.txt
robotoff-1.28.0.dist-info/WHEEL
robotoff-1.28.0.dist-info/METADATA
robotoff-1.28.0.dist-info/RECORD
